information/__init__.py
information/countries/Countries.py
information/countries/Country.py
information/countries/__init__.py
information/gics/__init__.py
information/gics/classify_sector.py
information/gics/get_gics_table.py
information/wikipedia/IosDevices.py
information/wikipedia/ListPage.py
information/wikipedia/SpecialPage.py
information/wikipedia/WikipediaEntities.py
information/wikipedia/WikipediaList.py
information/wikipedia/WikipediaListGuide.py
information/wikipedia/WikipediaLists.py
information/wikipedia/__init__.py
information/wikipedia/lists/__init__.py
information/wikipedia/lists/brands.py
information/wikipedia/lists/companies.py
information/wikipedia/lists/concepts.py
information/wikipedia/lists/diseases.py
information/wikipedia/lists/fictional_characters.py
information/wikipedia/lists/geographical_features.py
information/wikipedia/lists/historic_events.py
information/wikipedia/lists/landmarks.py
information/wikipedia/lists/music_bands.py
information/wikipedia/lists/organizations.py
information/wikipedia/lists/persons.py
information/wikipedia/lists/political_entities.py
information/wikipedia/lists/products.py
information/wikipedia/lists/space_objects.py
information/wikipedia/lists/species.py
information/wikipedia/lists/supernatural_beings.py
information/wikipedia/lists/vehicles.py
information/wikipedia/lists/weapons.py
information/wikipedia/signature/PageSignature.py
information/wikipedia/signature/__init__.py
information/wikipedia/signature/get_header_tokens.py
information/wikipedia/signature/get_important_tokens.py
information/wikipedia/signature/get_paragraph_statistics.py
information/wikipedia/signature/get_signature.py
information/wikipedia/signature/get_title_indicator.py
information/wikipedia/signature/tokenize.py
information-2020.7.26.dist-info/METADATA
information-2020.7.26.dist-info/WHEEL
information-2020.7.26.dist-info/top_level.txt
information-2020.7.26.dist-info/RECORD
