Metadata-Version: 2.1
Name: information
Version: 2020.7.26
Summary: Python library for knowledge
Home-page: https://github.com/idin/information
Author: Idin
Author-email: py@idin.ca
License: MIT
Platform: UNKNOWN
Classifier: Development Status :: 3 - Alpha
Classifier: Intended Audience :: Developers
Classifier: Programming Language :: Python :: 3 :: Only
Classifier: Programming Language :: Python :: 3.6
Classifier: Programming Language :: Python :: 3.7
Classifier: Topic :: Software Development :: Libraries :: Python Modules
Requires-Python: ~=3.6
Requires-Dist: pandas
Requires-Dist: numpy
Requires-Dist: joblib
Requires-Dist: pycountry
Requires-Dist: nltk
Requires-Dist: internet
Requires-Dist: chronometry
Requires-Dist: pensieve
Requires-Dist: silverware
Requires-Dist: linguistics
Requires-Dist: ravenclaw
Requires-Dist: disk
